modelgenerator/__init__.py
modelgenerator/callbacks.py
modelgenerator/lr_schedulers.py
modelgenerator/main.py
modelgenerator/metrics.py
modelgenerator/adapters/__init__.py
modelgenerator/adapters/adapters.py
modelgenerator/adapters/base.py
modelgenerator/adapters/fusion.py
modelgenerator/backbones/__init__.py
modelgenerator/backbones/backbones.py
modelgenerator/backbones/base.py
modelgenerator/cell/utils.py
modelgenerator/cell/gene_lists/OS_scRNA_gene_index.19264.tsv
modelgenerator/cell/gene_lists/geneformer_genes.csv
modelgenerator/cell/gene_lists/scimilarity_genes.tsv
modelgenerator/data/__init__.py
modelgenerator/data/base.py
modelgenerator/data/data.py
modelgenerator/distributed/__init__.py
modelgenerator/distributed/fsdp/__init__.py
modelgenerator/distributed/fsdp/wrap.py
modelgenerator/huggingface_models/__init__.py
modelgenerator/huggingface_models/utils.py
modelgenerator/huggingface_models/borzoi_pytorch/LICENSE
modelgenerator/huggingface_models/borzoi_pytorch/__init__.py
modelgenerator/huggingface_models/borzoi_pytorch/config_borzoi.py
modelgenerator/huggingface_models/borzoi_pytorch/gene_utils.py
modelgenerator/huggingface_models/borzoi_pytorch/pytorch_borzoi_helpers.py
modelgenerator/huggingface_models/borzoi_pytorch/pytorch_borzoi_model.py
modelgenerator/huggingface_models/borzoi_pytorch/pytorch_borzoi_transformer.py
modelgenerator/huggingface_models/borzoi_pytorch/pytorch_borzoi_utils.py
modelgenerator/huggingface_models/borzoi_pytorch/precomputed/targets.txt
modelgenerator/huggingface_models/cellfoundation/__init__.py
modelgenerator/huggingface_models/cellfoundation/configuration_cellfoundation.py
modelgenerator/huggingface_models/cellfoundation/modeling_cellfoundation.py
modelgenerator/huggingface_models/cellspatialfoundation/__init__.py
modelgenerator/huggingface_models/cellspatialfoundation/configuration_cellspatialfoundation.py
modelgenerator/huggingface_models/cellspatialfoundation/modeling_cellspatialfoundation.py
modelgenerator-0.1.3.post0.dist-info/METADATA
modelgenerator-0.1.3.post0.dist-info/WHEEL
modelgenerator-0.1.3.post0.dist-info/entry_points.txt
modelgenerator-0.1.3.post0.dist-info/licenses/LICENSE
modelgenerator-0.1.3.post0.dist-info/RECORD
