Metadata-Version: 2.4
Name: modelgenerator
Version: 0.1.3.post0
Summary: AIDO.ModelGenerator is a software stack powering the development of an AI-driven Digital Organism by enabling researchers to adapt pretrained models and generate finetuned models for downstream tasks.
Project-URL: Homepage, https://genbio-ai.github.io/ModelGenerator
Project-URL: Source, https://github.com/genbio-ai/ModelGenerator
Author: GenBio AI
Author-email: Caleb Ellington <caleb.ellington@genbio.ai>, Dian Li <dian.li@genbio.ai>
License-File: LICENSE
Keywords: finetuning,foundation models,genbio,machine learning
Classifier: Operating System :: OS Independent
Classifier: Programming Language :: Python :: 3
Requires-Python: <3.13,>=3.10
Requires-Dist: anndata
Requires-Dist: bionty==1.3.2
Requires-Dist: biopython>=1.84
Requires-Dist: biotite>=1.0.1
Requires-Dist: bitsandbytes
Requires-Dist: datasets>=2.14.6
Requires-Dist: dm-tree>=0.1.8
Requires-Dist: docstring-inheritance<=2.2.1
Requires-Dist: einops>=0.8.0
Requires-Dist: enformer-pytorch
Requires-Dist: jsonargparse[signatures]>=4.37.0
Requires-Dist: lightning>=2.4.0
Requires-Dist: lmdb
Requires-Dist: local-attention
Requires-Dist: ml-collections>=1.0.0
Requires-Dist: numpy<2
Requires-Dist: omegaconf>=2.3.0
Requires-Dist: packaging
Requires-Dist: pandas
Requires-Dist: peft<=0.13.2
Requires-Dist: pyfaidx
Requires-Dist: scikit-learn
Requires-Dist: scipy
Requires-Dist: tiledb==0.33.6
Requires-Dist: tiledbsoma-ml==0.1.0
Requires-Dist: tiledbsoma==1.16.1
Requires-Dist: torch
Requires-Dist: torchmetrics>=1.5.0
Requires-Dist: transformers==4.38.0
Requires-Dist: wandb
Provides-Extra: dev
Requires-Dist: griffe-inherited-docstrings==1.1.1; extra == 'dev'
Requires-Dist: mkdocs-material==9.5.44; extra == 'dev'
Requires-Dist: mkdocstrings-python==1.12.2; extra == 'dev'
Requires-Dist: pre-commit; extra == 'dev'
Requires-Dist: pytest; extra == 'dev'
Requires-Dist: pytest-cov; extra == 'dev'
Provides-Extra: flash-attn
Requires-Dist: flash-attn==2.7.4.post1; extra == 'flash-attn'
Requires-Dist: torch==2.6.0; extra == 'flash-attn'
